pythons_musicals/__init__.py
pythons_musicals/load_music.py
pythons_musicals/notes.py
pythons_musicals/zvuk-notyi-do.wav
pythons_musicals/zvuk-notyi-fa.wav
pythons_musicals/zvuk-notyi-lya.wav
pythons_musicals/zvuk-notyi-mi.wav
pythons_musicals/zvuk-notyi-re.wav
pythons_musicals/zvuk-notyi-si.wav
pythons_musicals/zvuk-notyi-sol.wav
pythons_musicals-1.1.0.4.dist-info/METADATA
pythons_musicals-1.1.0.4.dist-info/WHEEL
pythons_musicals-1.1.0.4.dist-info/RECORD
