Metadata-Version: 2.3
Name: pythons_musicals
Version: 1.1.0.4
Summary: This library can play sounds and your music.
Author: JUMP10
Requires-Python: >=3.2
Classifier: Programming Language :: Python :: 3
Classifier: Programming Language :: Python :: 3.13
Requires-Dist: asttokens (>=3.0.0,<4.0.0)
Requires-Dist: colorama (>=0.4.6,<0.5.0)
Requires-Dist: executing (>=2.2.0,<3.0.0)
Requires-Dist: loguru (>=0.7.3,<0.8.0)
Requires-Dist: pygments (>=2.19.1,<3.0.0)
Requires-Dist: rich (>=14.0.0,<15.0.0)
Requires-Dist: ruff (>=0.11.13,<0.12.0)
Project-URL: Homepage, https://www.pypi.org/project/pythons_musicals
